flowmaps_data/__init__.py
flowmaps_data/__main__.py
flowmaps_data/commands.py
flowmaps_data/data.py
flowmaps_data/main.py
flowmaps_data/utils.py
flowmaps_data-0.0.25.dist-info/LICENSE
flowmaps_data-0.0.25.dist-info/METADATA
flowmaps_data-0.0.25.dist-info/WHEEL
flowmaps_data-0.0.25.dist-info/entry_points.txt
flowmaps_data-0.0.25.dist-info/top_level.txt
flowmaps_data-0.0.25.dist-info/RECORD
