Metadata-Version: 2.1
Name: flowmaps-data
Version: 0.0.25
Summary: A tool for downloading Spanish COVID-19 and mobility data
Home-page: https://flowmaps.life.bsc.es/flowboard/data
Author: Javier del Valle Contreras
Author-email: javier.delvalle@bsc.es
License: UNKNOWN
Platform: UNKNOWN
Classifier: Programming Language :: Python :: 3
Classifier: License :: OSI Approved :: MIT License
Classifier: Operating System :: OS Independent
Requires-Python: >=3.6
License-File: LICENSE
Requires-Dist: pytz
Requires-Dist: progress
Requires-Dist: pandas
Requires-Dist: requests
Requires-Dist: python-dateutil
Requires-Dist: parquet
Requires-Dist: pyarrow
